pyini/__init__.py
pyini/configparser.py
pyini-0.1.1.dist-info/LICENSE
pyini-0.1.1.dist-info/METADATA
pyini-0.1.1.dist-info/WHEEL
pyini-0.1.1.dist-info/top_level.txt
pyini-0.1.1.dist-info/RECORD
