Metadata-Version: 2.1
Name: pyini
Version: 0.1.1
Summary: INI configuration file parser with useful standard extensions.
Home-page: https://github.com/Kieran-Bacon/pyini
Author: Kieran Bacon
Author-email: Kieran.Bacon@outlook.com
License: UNKNOWN
Platform: UNKNOWN
Classifier: Programming Language :: Python :: 3
Classifier: License :: OSI Approved :: MIT License
